Metadata-Version: 2.4
Name: david-oceanbase-mcp
Version: 0.0.3
Summary: A Model Context Protocol (MCP) server that enables secure interaction with OceanBase databases. This server allows AI assistants to list tables, read data, and execute SQL queries through a controlled interface, making database exploration and analysis safer and more structured.
License:                                  Apache License
Keywords: oceanbase,mcp
Classifier: Development Status :: 3 - Alpha
Classifier: Programming Language :: Python :: 3
Classifier: Programming Language :: Python :: 3.11
Requires-Python: >=3.11
License-File: LICENSE
Requires-Dist: mcp>=1.13.1
Requires-Dist: fastmcp>=2.12.0
Requires-Dist: mysql-connector-python>=9.1.0
Requires-Dist: SQLAlchemy>=2.0.32
Requires-Dist: beautifulsoup4>=4.13.5
Requires-Dist: pydantic>=2.11.7
Requires-Dist: python-dotenv>=1.1.1
Requires-Dist: certifi>=2022.12.7
Provides-Extra: dev
Requires-Dist: ruff>=0.1.0; extra == "dev"
Requires-Dist: pytest>=7.0.0; extra == "dev"
Provides-Extra: memory
Requires-Dist: numpy>=1.21.0; extra == "memory"
Requires-Dist: pyobvector>=0.2.15; extra == "memory"
Requires-Dist: langchain-huggingface>=0.3.1; extra == "memory"
Requires-Dist: torch>=2.0.0; extra == "memory"
Requires-Dist: sentence-transformers>=2.2.2; extra == "memory"
Dynamic: license-file
